railroad/__init__.py
railroad/actions.py
railroad/dispatch.py
railroad/guard.py
railroad/railroad.py
railroad/rescue.py
railroad-0.5.0.dist-info/DESCRIPTION.rst
railroad-0.5.0.dist-info/METADATA
railroad-0.5.0.dist-info/RECORD
railroad-0.5.0.dist-info/WHEEL
railroad-0.5.0.dist-info/metadata.json
railroad-0.5.0.dist-info/top_level.txt
