Metadata-Version: 1.1
Name: railroad
Version: 0.5.0
Summary: A functional library for data processing.
Home-page: https://github.com/s-m-i-t-a/railroad
Author: Jindrich K. Smitka
Author-email: smitka.j@gmail.com
License: MIT
Keywords: railroad
Platform: UNKNOWN
Classifier: Development Status :: 2 - Pre-Alpha
Classifier: Intended Audience :: Developers
Classifier: License :: OSI Approved :: MIT License
Classifier: Natural Language :: English
Classifier: Programming Language :: Python :: 2
Classifier: Programming Language :: Python :: 2.7
Classifier: Programming Language :: Python :: 3
Classifier: Programming Language :: Python :: 3.3
Classifier: Programming Language :: Python :: 3.4
